oomf/__init__.py
oomf/elements.py
oomf/gslib.py
oomf/utils.py
oomf-0.0.12.dist-info/LICENSE
oomf-0.0.12.dist-info/METADATA
oomf-0.0.12.dist-info/WHEEL
oomf-0.0.12.dist-info/top_level.txt
oomf-0.0.12.dist-info/RECORD
