Metadata-Version: 2.1
Name: oomf
Version: 0.0.12
Summary: Obvious Open Mining Format
Home-page: https://github.com/ericbdaniels/oomf
Author: Eric Daniels
License: MIT
Platform: UNKNOWN
Requires-Python: >=3.6
License-File: LICENSE
Requires-Dist: pandas (>=1.0.0)
Requires-Dist: numpy (>=1.19.2)
Requires-Dist: omf (==1.0.1)
Requires-Dist: omfvista (==0.2.2)
Requires-Dist: rich (>=9.0.0)
